{
  "code": "E07000179",
  "name": "South Oxfordshire",
  "region_code": "E12000008",
  "region_name": "South East",
  "country_code": "E92000001",
  "country_name": "England",
  "ew_code": "K04000001",
  "ew_name": "England and Wales",
  "data": {
    "population": {
      "perc": {
        "1981": {
          "female": 50.69,
          "male": 49.31
        },
        "1991": {
          "female": 51.0,
          "male": 49.0
        },
        "2001": {
          "female": 49.31,
          "male": 50.69
        },
        "2011": {
          "female": 49.16,
          "male": 50.84
        },
        "change": {
          "female": -0.15,
          "male": 0.15
        }
      },
      "perc_rank": {
        "1981": {
          "female": 79.0,
          "male": 270.0
        },
        "1991": {
          "female": 76.0,
          "male": 273.0
        },
        "2001": {
          "female": 285.0,
          "male": 62.0
        },
        "2011": {
          "female": 187.0,
          "male": 159.0
        },
        "change": {
          "female": 32.0,
          "male": 316.0
        }
      },
      "value": {
        "1981": {
          "all": 114824.0,
          "female": 58201.0,
          "male": 56623.0
        },
        "1991": {
          "all": 112907.0,
          "female": 57584.0,
          "male": 55323.0
        },
        "2001": {
          "all": 128188.0,
          "female": 63208.0,
          "male": 64980.0
        },
        "2011": {
          "all": 134257.0,
          "female": 66005.0,
          "male": 68252.0
        },
        "change": {
          "all": 4.73,
          "female": 4.43,
          "male": 5.04
        }
      },
      "value_rank": {
        "1981": {
          "all": 198.0,
          "female": 190.0,
          "male": 205.0
        },
        "1991": {
          "all": 187.0,
          "female": 183.0,
          "male": 189.0
        },
        "2001": {
          "all": 192.0,
          "female": 196.0,
          "male": 189.0
        },
        "2011": {
          "all": 188.0,
          "female": 188.0,
          "male": 186.0
        },
        "change": {
          "all": 102.0,
          "female": 79.0,
          "male": 150.0
        }
      }
    },
    "age10yr": {
      "perc": {
        "1981": {
          "0-9": 12.79,
          "10-19": 17.22,
          "20-29": 12.92,
          "30-39": 15.15,
          "40-49": 12.58,
          "50-59": 11.4,
          "60-69": 8.95,
          "70plus": 8.98
        },
        "1991": {
          "0-9": 12.56,
          "10-19": 12.56,
          "20-29": 14.67,
          "30-39": 14.21,
          "40-49": 15.21,
          "50-59": 11.45,
          "60-69": 9.27,
          "70plus": 10.07
        },
        "2001": {
          "0-9": 12.63,
          "10-19": 12.08,
          "20-29": 10.28,
          "30-39": 16.66,
          "40-49": 14.45,
          "50-59": 13.6,
          "60-69": 9.34,
          "70plus": 10.96
        },
        "2011": {
          "0-9": 11.96,
          "10-19": 11.88,
          "20-29": 9.96,
          "30-39": 12.49,
          "40-49": 16.07,
          "50-59": 12.99,
          "60-69": 11.9,
          "70plus": 12.76
        },
        "change": {
          "0-9": -0.67,
          "10-19": -0.2,
          "20-29": -0.32,
          "30-39": -4.17,
          "40-49": 1.62,
          "50-59": -0.61,
          "60-69": 2.56,
          "70plus": 1.8
        }
      },
      "perc_rank": {
        "1981": {
          "0-9": 191.0,
          "10-19": 285.0,
          "20-29": 122.0,
          "30-39": 260.0,
          "40-49": 323.0,
          "50-59": 130.0,
          "60-69": 59.0,
          "70plus": 126.0
        },
        "1991": {
          "0-9": 166.0,
          "10-19": 179.0,
          "20-29": 175.0,
          "30-39": 233.0,
          "40-49": 287.0,
          "50-59": 283.0,
          "60-69": 77.0,
          "70plus": 105.0
        },
        "2001": {
          "0-9": 235.0,
          "10-19": 90.0,
          "20-29": 114.0,
          "30-39": 291.0,
          "40-49": 307.0,
          "50-59": 202.0,
          "60-69": 145.0,
          "70plus": 126.0
        },
        "2011": {
          "0-9": 225.0,
          "10-19": 126.0,
          "20-29": 77.0,
          "30-39": 185.0,
          "40-49": 320.0,
          "50-59": 204.0,
          "60-69": 190.0,
          "70plus": 199.0
        },
        "change": {
          "0-9": 185.0,
          "10-19": 258.0,
          "20-29": 57.0,
          "30-39": 17.0,
          "40-49": 250.0,
          "50-59": 167.0,
          "60-69": 227.0,
          "70plus": 312.0
        }
      },
      "value": {
        "1981": {
          "0-9": 14888.0,
          "10-19": 20049.0,
          "20-29": 15039.0,
          "30-39": 17632.0,
          "40-49": 14640.0,
          "50-59": 13274.0,
          "60-69": 10420.0,
          "70plus": 10458.0,
          "all": 116400.0
        },
        "1991": {
          "0-9": 15008.0,
          "10-19": 15008.0,
          "20-29": 17523.0,
          "30-39": 16976.0,
          "40-49": 18169.0,
          "50-59": 13681.0,
          "60-69": 11075.0,
          "70plus": 12036.0,
          "all": 119476.0
        },
        "2001": {
          "0-9": 16185.0,
          "10-19": 15490.0,
          "20-29": 13183.0,
          "30-39": 21362.0,
          "40-49": 18518.0,
          "50-59": 17431.0,
          "60-69": 11968.0,
          "70plus": 14050.0,
          "all": 128187.0
        },
        "2011": {
          "0-9": 16056.0,
          "10-19": 15951.0,
          "20-29": 13369.0,
          "30-39": 16773.0,
          "40-49": 21570.0,
          "50-59": 17436.0,
          "60-69": 15977.0,
          "70plus": 17125.0,
          "all": 134257.0
        },
        "change": {
          "0-9": -0.8,
          "10-19": 2.98,
          "20-29": 1.41,
          "30-39": -21.48,
          "40-49": 16.48,
          "50-59": 0.03,
          "60-69": 33.5,
          "70plus": 21.89,
          "all": 4.74
        }
      },
      "value_rank": {
        "1981": {
          "0-9": 203.0,
          "10-19": 214.0,
          "20-29": 193.0,
          "30-39": 210.0,
          "40-49": 220.0,
          "50-59": 201.0,
          "60-69": 163.0,
          "70plus": 174.0,
          "all": 199.0
        },
        "1991": {
          "0-9": 195.0,
          "10-19": 200.0,
          "20-29": 195.0,
          "30-39": 202.0,
          "40-49": 217.0,
          "50-59": 211.0,
          "60-69": 158.0,
          "70plus": 153.0,
          "all": 192.0
        },
        "2001": {
          "0-9": 206.0,
          "10-19": 188.0,
          "20-29": 182.0,
          "30-39": 216.0,
          "40-49": 212.0,
          "50-59": 208.0,
          "60-69": 187.0,
          "70plus": 163.0,
          "all": 192.0
        },
        "2011": {
          "0-9": 202.0,
          "10-19": 190.0,
          "20-29": 164.0,
          "30-39": 193.0,
          "40-49": 209.0,
          "50-59": 202.0,
          "60-69": 198.0,
          "70plus": 197.0,
          "all": 188.0
        },
        "change": {
          "0-9": 155.0,
          "10-19": 192.0,
          "20-29": 40.0,
          "30-39": 59.0,
          "40-49": 158.0,
          "50-59": 136.0,
          "60-69": 229.0,
          "70plus": 306.0,
          "all": 102.0
        }
      }
    },
    "density": {
      "value": {
        "1981": {
          "all": 1.69
        },
        "1991": {
          "all": 1.66
        },
        "2001": {
          "all": 1.89
        },
        "2011": {
          "all": 1.98
        },
        "change": {
          "all": 4.76
        }
      },
      "value_rank": {
        "1981": {
          "all": 91.0
        },
        "1991": {
          "all": 89.0
        },
        "2001": {
          "all": 91.0
        },
        "2011": {
          "all": 87.0
        },
        "change": {
          "all": 104.0
        }
      }
    },
    "agemed": {
      "value": {
        "1981": {
          "all": 35.0
        },
        "1991": {
          "all": 36.0
        },
        "2001": {
          "all": 38.0
        },
        "2011": {
          "all": 39.0
        },
        "change": {
          "all": 2.63
        }
      },
      "value_rank": {
        "1981": {
          "all": 72.0
        },
        "1991": {
          "all": 65.0
        },
        "2001": {
          "all": 150.0
        },
        "2011": {
          "all": 156.0
        },
        "change": {
          "all": 165.0
        }
      }
    }
  }
}