{
  "code": "E14000595",
  "name": "Bridgwater and West Somerset",
  "region_code": "E12000009",
  "region_name": "South West",
  "country_code": "E92000001",
  "country_name": "England",
  "ew_code": "K04000001",
  "ew_name": "England and Wales",
  "data": {
    "population": {
      "perc": {
        "2001": {
          "female": 51.54,
          "male": 48.46
        },
        "2011": {
          "female": 51.25,
          "male": 48.75
        },
        "change": {
          "female": -0.29,
          "male": 0.29
        }
      },
      "perc_rank": {
        "2001": {
          "female": 362.0,
          "male": 206.0
        },
        "2011": {
          "female": 401.0,
          "male": 167.0
        },
        "change": {
          "female": 331.0,
          "male": 238.0
        }
      },
      "value": {
        "2001": {
          "all": 101300.0,
          "female": 52207.0,
          "male": 49093.0
        },
        "2011": {
          "all": 106450.0,
          "female": 54556.0,
          "male": 51894.0
        },
        "change": {
          "all": 5.08,
          "female": 4.5,
          "male": 5.71
        }
      },
      "value_rank": {
        "2001": {
          "all": 514.0,
          "female": 519.0,
          "male": 499.0
        },
        "2011": {
          "all": 452.0,
          "female": 474.0,
          "male": 438.0
        },
        "change": {
          "all": 215.0,
          "female": 228.0,
          "male": 219.0
        }
      }
    },
    "age10yr": {
      "perc": {
        "2001": {
          "0-9": 11.41,
          "10-19": 12.33,
          "20-29": 8.98,
          "30-39": 13.63,
          "40-49": 13.15,
          "50-59": 14.23,
          "60-69": 11.28,
          "70plus": 14.99
        },
        "2011": {
          "0-9": 10.29,
          "10-19": 13.75,
          "20-29": 18.5,
          "30-39": 14.09,
          "40-49": 13.71,
          "50-59": 14.08,
          "60-69": 9.25,
          "70plus": 6.32
        },
        "change": {
          "0-9": -1.12,
          "10-19": 1.42,
          "20-29": 9.52,
          "30-39": 0.46,
          "40-49": 0.56,
          "50-59": -0.15,
          "60-69": -2.03,
          "70plus": -8.67
        }
      },
      "perc_rank": {
        "2001": {
          "0-9": 152.0,
          "10-19": 195.0,
          "20-29": 54.0,
          "30-39": 79.0,
          "40-49": 212.0,
          "50-59": 447.0,
          "60-69": 520.0,
          "70plus": 526.0
        },
        "2011": {
          "0-9": 102.0,
          "10-19": 155.0,
          "20-29": 80.0,
          "30-39": 148.0,
          "40-49": 490.0,
          "50-59": 511.0,
          "60-69": 510.0,
          "70plus": 519.0
        },
        "change": {
          "0-9": 124.0,
          "10-19": 236.0,
          "20-29": 147.0,
          "30-39": 420.0,
          "40-49": 549.0,
          "50-59": 530.0,
          "60-69": 350.0,
          "70plus": 49.0
        }
      },
      "value": {
        "2001": {
          "0-9": 11545.0,
          "10-19": 12478.0,
          "20-29": 9089.0,
          "30-39": 13801.0,
          "40-49": 13306.0,
          "50-59": 14408.0,
          "60-69": 11421.0,
          "70plus": 15172.0,
          "all": 101220.0
        },
        "2011": {
          "0-9": 10959.0,
          "10-19": 14633.0,
          "20-29": 19693.0,
          "30-39": 15004.0,
          "40-49": 14592.0,
          "50-59": 14990.0,
          "60-69": 9850.0,
          "70plus": 6729.0,
          "all": 106450.0
        },
        "change": {
          "0-9": -5.08,
          "10-19": 17.27,
          "20-29": 116.67,
          "30-39": 8.72,
          "40-49": 9.66,
          "50-59": 4.04,
          "60-69": -13.76,
          "70plus": -55.65,
          "all": 5.17
        }
      },
      "value_rank": {
        "2001": {
          "0-9": 357.0,
          "10-19": 414.0,
          "20-29": 173.0,
          "30-39": 280.0,
          "40-49": 458.0,
          "50-59": 566.0,
          "60-69": 570.0,
          "70plus": 557.0,
          "all": 512.0
        },
        "2011": {
          "0-9": 261.0,
          "10-19": 355.0,
          "20-29": 205.0,
          "30-39": 375.0,
          "40-49": 565.0,
          "50-59": 564.0,
          "60-69": 555.0,
          "70plus": 552.0,
          "all": 452.0
        },
        "change": {
          "0-9": 130.0,
          "10-19": 207.0,
          "20-29": 400.0,
          "30-39": 413.0,
          "40-49": 539.0,
          "50-59": 521.0,
          "60-69": 444.0,
          "70plus": 343.0,
          "all": 224.0
        }
      }
    },
    "density": {
      "value": {
        "2001": {
          "all": 0.94
        },
        "2011": {
          "all": 0.99
        },
        "change": {
          "all": 5.32
        }
      },
      "value_rank": {
        "2001": {
          "all": 36.0
        },
        "2011": {
          "all": 35.0
        },
        "change": {
          "all": 227.0
        }
      }
    },
    "agemed": {
      "value": {
        "2001": {
          "all": 40.0
        },
        "2011": {
          "all": 35.0
        },
        "change": {
          "all": -12.5
        }
      },
      "value_rank": {
        "2001": {
          "all": 473.0
        },
        "2011": {
          "all": 456.0
        },
        "change": {
          "all": 386.0
        }
      }
    }
  }
}