{
  "code": "E14000912",
  "name": "Salisbury",
  "region_code": "E12000009",
  "region_name": "South West",
  "country_code": "E92000001",
  "country_name": "England",
  "ew_code": "K04000001",
  "ew_name": "England and Wales",
  "data": {
    "population": {
      "perc": {
        "2001": {
          "female": 51.73,
          "male": 48.27
        },
        "2011": {
          "female": 51.9,
          "male": 48.1
        },
        "change": {
          "female": 0.17,
          "male": -0.17
        }
      },
      "perc_rank": {
        "2001": {
          "female": 416.0,
          "male": 156.0
        },
        "2011": {
          "female": 538.0,
          "male": 34.0
        },
        "change": {
          "female": 521.0,
          "male": 52.0
        }
      },
      "value": {
        "2001": {
          "all": 87369.0,
          "female": 45193.0,
          "male": 42176.0
        },
        "2011": {
          "all": 91498.0,
          "female": 47490.0,
          "male": 44008.0
        },
        "change": {
          "all": 4.73,
          "female": 5.08,
          "male": 4.34
        }
      },
      "value_rank": {
        "2001": {
          "all": 170.0,
          "female": 190.0,
          "male": 170.0
        },
        "2011": {
          "all": 166.0,
          "female": 200.0,
          "male": 146.0
        },
        "change": {
          "all": 198.0,
          "female": 260.0,
          "male": 143.0
        }
      }
    },
    "age10yr": {
      "perc": {
        "2001": {
          "0-9": 11.64,
          "10-19": 11.67,
          "20-29": 10.28,
          "30-39": 14.92,
          "40-49": 13.96,
          "50-59": 13.55,
          "60-69": 10.29,
          "70plus": 13.69
        },
        "2011": {
          "0-9": 11.27,
          "10-19": 13.5,
          "20-29": 20.12,
          "30-39": 15.19,
          "40-49": 13.34,
          "50-59": 12.1,
          "60-69": 8.32,
          "70plus": 6.17
        },
        "change": {
          "0-9": -0.37,
          "10-19": 1.83,
          "20-29": 9.84,
          "30-39": 0.27,
          "40-49": -0.62,
          "50-59": -1.45,
          "60-69": -1.97,
          "70plus": -7.52
        }
      },
      "perc_rank": {
        "2001": {
          "0-9": 189.0,
          "10-19": 73.0,
          "20-29": 172.0,
          "30-39": 237.0,
          "40-49": 415.0,
          "50-59": 357.0,
          "60-69": 408.0,
          "70plus": 476.0
        },
        "2011": {
          "0-9": 243.0,
          "10-19": 122.0,
          "20-29": 162.0,
          "30-39": 361.0,
          "40-49": 429.0,
          "50-59": 368.0,
          "60-69": 425.0,
          "70plus": 506.0
        },
        "change": {
          "0-9": 365.0,
          "10-19": 342.0,
          "20-29": 168.0,
          "30-39": 389.0,
          "40-49": 390.0,
          "50-59": 363.0,
          "60-69": 392.0,
          "70plus": 158.0
        }
      },
      "value": {
        "2001": {
          "0-9": 10187.0,
          "10-19": 10212.0,
          "20-29": 8992.0,
          "30-39": 13060.0,
          "40-49": 12217.0,
          "50-59": 11856.0,
          "60-69": 9008.0,
          "70plus": 11980.0,
          "all": 87512.0
        },
        "2011": {
          "0-9": 10308.0,
          "10-19": 12354.0,
          "20-29": 18406.0,
          "30-39": 13901.0,
          "40-49": 12203.0,
          "50-59": 11072.0,
          "60-69": 7612.0,
          "70plus": 5642.0,
          "all": 91498.0
        },
        "change": {
          "0-9": 1.19,
          "10-19": 20.98,
          "20-29": 104.69,
          "30-39": 6.44,
          "40-49": -0.11,
          "50-59": -6.61,
          "60-69": -15.5,
          "70plus": -52.9,
          "all": 4.55
        }
      },
      "value_rank": {
        "2001": {
          "0-9": 174.0,
          "10-19": 104.0,
          "20-29": 160.0,
          "30-39": 203.0,
          "40-49": 294.0,
          "50-59": 325.0,
          "60-69": 395.0,
          "70plus": 474.0,
          "all": 176.0
        },
        "2011": {
          "0-9": 189.0,
          "10-19": 114.0,
          "20-29": 152.0,
          "30-39": 239.0,
          "40-49": 331.0,
          "50-59": 339.0,
          "60-69": 413.0,
          "70plus": 492.0,
          "all": 166.0
        },
        "change": {
          "0-9": 288.0,
          "10-19": 287.0,
          "20-29": 239.0,
          "30-39": 357.0,
          "40-49": 379.0,
          "50-59": 360.0,
          "60-69": 385.0,
          "70plus": 482.0,
          "all": 187.0
        }
      }
    },
    "density": {
      "value": {
        "2001": {
          "all": 1.43
        },
        "2011": {
          "all": 1.49
        },
        "change": {
          "all": 4.2
        }
      },
      "value_rank": {
        "2001": {
          "all": 80.0
        },
        "2011": {
          "all": 78.0
        },
        "change": {
          "all": 168.0
        }
      }
    },
    "agemed": {
      "value": {
        "2001": {
          "all": 39.0
        },
        "2011": {
          "all": 34.0
        },
        "change": {
          "all": -12.82
        }
      },
      "value_rank": {
        "2001": {
          "all": 384.0
        },
        "2011": {
          "all": 378.0
        },
        "change": {
          "all": 337.0
        }
      }
    }
  }
}