{
  "code": "E14000650",
  "name": "Coventry North West",
  "region_code": "E12000005",
  "region_name": "West Midlands",
  "country_code": "E92000001",
  "country_name": "England",
  "ew_code": "K04000001",
  "ew_name": "England and Wales",
  "data": {
    "population": {
      "perc": {
        "2001": {
          "female": 50.5,
          "male": 49.5
        },
        "2011": {
          "female": 50.71,
          "male": 49.29
        },
        "change": {
          "female": 0.21,
          "male": -0.21
        }
      },
      "perc_rank": {
        "2001": {
          "female": 66.0,
          "male": 505.0
        },
        "2011": {
          "female": 203.0,
          "male": 363.0
        },
        "change": {
          "female": 528.0,
          "male": 42.0
        }
      },
      "value": {
        "2001": {
          "all": 97789.0,
          "female": 49381.0,
          "male": 48408.0
        },
        "2011": {
          "all": 100872.0,
          "female": 51155.0,
          "male": 49717.0
        },
        "change": {
          "all": 3.15,
          "female": 3.59,
          "male": 2.7
        }
      },
      "value_rank": {
        "2001": {
          "all": 465.0,
          "female": 426.0,
          "male": 477.0
        },
        "2011": {
          "all": 363.0,
          "female": 359.0,
          "male": 370.0
        },
        "change": {
          "all": 117.0,
          "female": 177.0,
          "male": 79.0
        }
      }
    },
    "age10yr": {
      "perc": {
        "2001": {
          "0-9": 12.32,
          "10-19": 12.84,
          "20-29": 14.45,
          "30-39": 15.43,
          "40-49": 12.25,
          "50-59": 11.28,
          "60-69": 9.23,
          "70plus": 12.19
        },
        "2011": {
          "0-9": 12.36,
          "10-19": 15.46,
          "20-29": 26.11,
          "30-39": 14.06,
          "40-49": 10.64,
          "50-59": 9.69,
          "60-69": 6.92,
          "70plus": 4.77
        },
        "change": {
          "0-9": 0.04,
          "10-19": 2.62,
          "20-29": 11.66,
          "30-39": -1.37,
          "40-49": -1.61,
          "50-59": -1.59,
          "60-69": -2.31,
          "70plus": -7.42
        }
      },
      "perc_rank": {
        "2001": {
          "0-9": 305.0,
          "10-19": 317.0,
          "20-29": 461.0,
          "30-39": 322.0,
          "40-49": 71.0,
          "50-59": 123.0,
          "60-69": 259.0,
          "70plus": 372.0
        },
        "2011": {
          "0-9": 407.0,
          "10-19": 442.0,
          "20-29": 441.0,
          "30-39": 143.0,
          "40-49": 98.0,
          "50-59": 169.0,
          "60-69": 237.0,
          "70plus": 319.0
        },
        "change": {
          "0-9": 451.0,
          "10-19": 477.0,
          "20-29": 377.0,
          "30-39": 148.0,
          "40-49": 164.0,
          "50-59": 336.0,
          "60-69": 195.0,
          "70plus": 176.0
        }
      },
      "value": {
        "2001": {
          "0-9": 12078.0,
          "10-19": 12586.0,
          "20-29": 14162.0,
          "30-39": 15123.0,
          "40-49": 12011.0,
          "50-59": 11057.0,
          "60-69": 9050.0,
          "70plus": 11943.0,
          "all": 98010.0
        },
        "2011": {
          "0-9": 12464.0,
          "10-19": 15592.0,
          "20-29": 26339.0,
          "30-39": 14187.0,
          "40-49": 10733.0,
          "50-59": 9773.0,
          "60-69": 6976.0,
          "70plus": 4808.0,
          "all": 100872.0
        },
        "change": {
          "0-9": 3.2,
          "10-19": 23.88,
          "20-29": 85.98,
          "30-39": -6.19,
          "40-49": -10.64,
          "50-59": -11.61,
          "60-69": -22.92,
          "70plus": -59.74,
          "all": 2.92
        }
      },
      "value_rank": {
        "2001": {
          "0-9": 418.0,
          "10-19": 432.0,
          "20-29": 469.0,
          "30-39": 412.0,
          "40-49": 254.0,
          "50-59": 227.0,
          "60-69": 402.0,
          "70plus": 471.0,
          "all": 467.0
        },
        "2011": {
          "0-9": 405.0,
          "10-19": 428.0,
          "20-29": 429.0,
          "30-39": 274.0,
          "40-49": 131.0,
          "50-59": 205.0,
          "60-69": 316.0,
          "70plus": 381.0,
          "all": 363.0
        },
        "change": {
          "0-9": 344.0,
          "10-19": 349.0,
          "20-29": 65.0,
          "30-39": 102.0,
          "40-49": 53.0,
          "50-59": 201.0,
          "60-69": 143.0,
          "70plus": 161.0,
          "all": 113.0
        }
      }
    },
    "density": {
      "value": {
        "2001": {
          "all": 25.51
        },
        "2011": {
          "all": 26.32
        },
        "change": {
          "all": 3.18
        }
      },
      "value_rank": {
        "2001": {
          "all": 400.0
        },
        "2011": {
          "all": 396.0
        },
        "change": {
          "all": 121.0
        }
      }
    },
    "agemed": {
      "value": {
        "2001": {
          "all": 37.0
        },
        "2011": {
          "all": 32.0
        },
        "change": {
          "all": -13.51
        }
      },
      "value_rank": {
        "2001": {
          "all": 180.0
        },
        "2011": {
          "all": 183.0
        },
        "change": {
          "all": 228.0
        }
      }
    }
  }
}